{
  "events": [
    {
      "id": 1,
      "title": "Code Father",
      "description": "Lorem ipsum dolor sit amet, consectetur adipisicing elit. Voluptatibus quia, nulla! Maiores et perferendis eaque, exercitationem praesentium nihil.",
      "imgsrc": "/images/dummy.jpg",
      "tags": ["photography", "travel", "winter"],
      "price": 500
    },
    {
      "id": 2,
      "title": "Tech Expo 2024",
      "description": "Explore the latest in technology and innovation. Join us for a day of exciting presentations and hands-on experiences.",
      "imgsrc": "/images/dummy.jpg",
      "tags": ["technology", "innovation", "exhibition"],
      "price": 250
    },
    {
      "id": 3,
      "title": "Startup Summit",
      "description": "Connect with industry leaders, investors, and fellow entrepreneurs. Gain insights and inspiration for your startup journey.",
      "imgsrc": "/images/dummy.jpg",
      "tags": ["startup", "entrepreneurship", "networking"],
      "price": 800
    }
  ]
}
